pymultimap/__about__.py
pymultimap/__init__.py
pymultimap/multimap.py
pymultimap-0.0.8.dist-info/METADATA
pymultimap-0.0.8.dist-info/WHEEL
pymultimap-0.0.8.dist-info/licenses/LICENSE.txt
pymultimap-0.0.8.dist-info/RECORD
