Metadata-Version: 2.4
Name: pymultimap
Version: 0.0.8
Project-URL: Documentation, https://github.com/sachinsachdeva/pymultimap#readme
Project-URL: Issues, https://github.com/sachinsachdeva/pymultimap/issues
Project-URL: Source, https://github.com/sachinsachdeva/pymultimap
Author-email: sachinsachdeva <7625278+sachinsachdeva@users.noreply.github.com>
License-Expression: MIT
License-File: LICENSE.txt
Classifier: Development Status :: 4 - Beta
Classifier: Programming Language :: Python
Classifier: Programming Language :: Python :: 3.8
Classifier: Programming Language :: Python :: 3.9
Classifier: Programming Language :: Python :: 3.10
Classifier: Programming Language :: Python :: 3.11
Classifier: Programming Language :: Python :: 3.12
Classifier: Programming Language :: Python :: Implementation :: CPython
Classifier: Programming Language :: Python :: Implementation :: PyPy
Requires-Python: >=3.8
Requires-Dist: sortedcontainers
